binformatlib.py
binformatlib-6.3.0.dist-info/METADATA
binformatlib-6.3.0.dist-info/WHEEL
binformatlib-6.3.0.dist-info/top_level.txt
binformatlib-6.3.0.dist-info/RECORD
