Metadata-Version: 2.4
Name: binformatlib
Version: 6.3.0
Summary: A beginner-friendly binary format packing/unpacking module with full hex and byte control.
Author: jony eldry
Author-email: umayashinderu@gmail.com
Classifier: Programming Language :: Python :: 3
Classifier: Intended Audience :: Developers
Classifier: License :: OSI Approved :: MIT License
Classifier: Topic :: File Formats
Classifier: Topic :: Software Development :: Libraries
Requires-Python: >=3.6
Dynamic: author
Dynamic: author-email
Dynamic: classifier
Dynamic: description
Dynamic: description-content-type
Dynamic: requires-python
Dynamic: summary
